gateway_4d_viewer/__init__.py
gateway_4d_viewer/__main__.py
gateway_4d_viewer/api_schema.py
gateway_4d_viewer/config.py
gateway_4d_viewer/dataset_helpers.py
gateway_4d_viewer/google_bucket_source.py
gateway_4d_viewer/interfaces.py
gateway_4d_viewer/routes_v1.py
gateway_4d_viewer/xcube_server_source.py
tests/__init__.py
tests/test_dataset_helpers.py
tests/test_google_bucket_source.py
tests/test_interfaces.py
tests/test_routes_api_v1.py
tests/test_xcube_server_source.py
gateway_4d_viewer-1.1.44.dist-info/METADATA
gateway_4d_viewer-1.1.44.dist-info/WHEEL
gateway_4d_viewer-1.1.44.dist-info/top_level.txt
gateway_4d_viewer-1.1.44.dist-info/RECORD
