Metadata-Version: 2.1
Name: gateway-4d-viewer
Version: 1.1.44
Summary: A flask-based gateway for serving data to Earthwave's 4d viewer client.
Home-page: https://earthwave.co.uk/
Author: Earthwave Ltd
Author-email: info@earthwave.co.uk
Requires-Python: >=3.9
Requires-Dist: flask
Requires-Dist: flask-cors
Requires-Dist: gunicorn
Requires-Dist: google-cloud-storage
Requires-Dist: google-api-core
Requires-Dist: schema
